systemdlogging/__init__.py
systemdlogging/backend_ctyped.py
systemdlogging/toolbox.py
systemd_logging-1.0.1.dist-info/AUTHORS
systemd_logging-1.0.1.dist-info/LICENSE
systemd_logging-1.0.1.dist-info/METADATA
systemd_logging-1.0.1.dist-info/WHEEL
systemd_logging-1.0.1.dist-info/top_level.txt
systemd_logging-1.0.1.dist-info/RECORD
